nucliadb_sdk/__init__.py
nucliadb_sdk/py.typed
nucliadb_sdk/tests/__init__.py
nucliadb_sdk/tests/fixtures.py
nucliadb_sdk/v2/__init__.py
nucliadb_sdk/v2/exceptions.py
nucliadb_sdk/v2/sdk.py
nucliadb_sdk-6.11.1.post5854.dist-info/METADATA
nucliadb_sdk-6.11.1.post5854.dist-info/WHEEL
nucliadb_sdk-6.11.1.post5854.dist-info/top_level.txt
nucliadb_sdk-6.11.1.post5854.dist-info/RECORD
