Metadata-Version: 2.4
Name: nucliadb_sdk
Version: 6.11.1.post5854
Summary: NucliaDB SDK
Author-email: Nuclia <nucliadb@nuclia.com>
License-Expression: Apache-2.0
Project-URL: Homepage, https://nuclia.com
Project-URL: Repository, https://github.com/nuclia/nucliadb
Classifier: Development Status :: 4 - Beta
Classifier: Intended Audience :: Developers
Classifier: Intended Audience :: Information Technology
Classifier: Topic :: Software Development :: Libraries :: Python Modules
Classifier: Programming Language :: Python
Classifier: Programming Language :: Python :: 3.10
Classifier: Programming Language :: Python :: 3.11
Classifier: Programming Language :: Python :: 3.12
Classifier: Programming Language :: Python :: 3 :: Only
Requires-Python: <4,>=3.10
Requires-Dist: httpx
Requires-Dist: orjson
Requires-Dist: pydantic>=2.6
Requires-Dist: nuclia-models>=0.50.0
Requires-Dist: nucliadb-models>=6.11.1.post5854
